nobita/__init__.py
nobita/modules/.DS_Store
nobita/modules/__init__.py
nobita/modules/base_module.py
nobita/modules/downstream.py
nobita/modules/models/age-gender-recognition-retail-0013_openvino_2021.2_6shave.blob
nobita/modules/models/emotions-recognition-retail-0003-shaves6.blob
nobita/modules/models/emotions-recognition-retail-0003.blob
nobita/modules/models/face-detection-adas-0001-shaves4.blob
nobita/modules/models/face-detection-adas-0001-shaves6.blob
nobita/modules/models/face-detection-retail-0004_openvino_2021.2_6shave.blob
nobita/modules/models/facial-landmarks-35-adas-0002-shaves4.blob
nobita/modules/models/facial-landmarks-35-adas-0002-shaves6.blob
nobita/modules/models/head-pose-estimation-adas-0001-shaves4.blob
nobita/modules/models/movenet_singlepose_lightning_U8_transpose.blob
nobita/modules/upstream.py
nobita/modules/utils.py
nobita/nobita_vision.py
nobita-0.0.1.dist-info/WHEEL
nobita-0.0.1.dist-info/METADATA
nobita-0.0.1.dist-info/RECORD
