Metadata-Version: 2.1
Name: nobita
Version: 0.0.1
Summary: 
Home-page: https://github.com/wbawakate/nobita
License: MIT
Author: all-in-one library for non-verbal communication of robots
Requires-Python: >=3.8
Classifier: License :: OSI Approved :: MIT License
Classifier: Programming Language :: Python :: 3
Classifier: Programming Language :: Python :: 3.8
Classifier: Programming Language :: Python :: 3.9
Requires-Dist: depthai (>=2.8.0,<3.0.0)
Requires-Dist: numpy (>=1.21.1,<2.0.0)
Requires-Dist: opencv-python (>=4.5.3,<5.0.0)
Project-URL: Repository, https://github.com/wbawakate/nobita
